setup.py
Util/__init__.py
Util/e_mail.py
Util/excel.py
Util/id_number.py
id_builder.egg-info/PKG-INFO
id_builder.egg-info/SOURCES.txt
id_builder.egg-info/dependency_links.txt
id_builder.egg-info/top_level.txt
id_builder.egg-info/zip-safe