Metadata-Version: 1.1
Name: id-builder
Version: 1.0.3
Summary: this is a package for building a ID number that is from china
Home-page: http://blog.useasp.net/
Author: SiQiLiu
Author-email: 976462397@qq.com
License: MIT
Keywords: test python package
Platform: UNKNOWN
Classifier: License :: OSI Approved :: MIT License
Classifier: Programming Language :: Python
Classifier: Intended Audience :: Developers
Classifier: Operating System :: OS Independent
